pyrovelocity/BUILD.bazel
pyrovelocity/__init__.py
pyrovelocity/__main__.py
pyrovelocity/analysis/__init__.py
pyrovelocity/analysis/analyze.py
pyrovelocity/analysis/cytotrace.py
pyrovelocity/analysis/subpopulation.py
pyrovelocity/analysis/trajectory.py
pyrovelocity/analysis/transcriptome_properties.py
pyrovelocity/interfaces.py
pyrovelocity/io/__init__.py
pyrovelocity/io/archive.py
pyrovelocity/io/cluster.py
pyrovelocity/io/compressedpickle.py
pyrovelocity/io/datasets.py
pyrovelocity/io/drive.py
pyrovelocity/io/ensembl.py
pyrovelocity/io/ensembl_batch.py
pyrovelocity/io/fetch.py
pyrovelocity/io/fsspec.py
pyrovelocity/io/gcs.py
pyrovelocity/io/hash.py
pyrovelocity/io/metrics.py
pyrovelocity/io/serialization.py
pyrovelocity/io/sparsity.py
pyrovelocity/io/subset_data.py
pyrovelocity/logging.py
pyrovelocity/metrics/__init__.py
pyrovelocity/metrics/criticality_index.py
pyrovelocity/metrics/hypersphere_distribution_divergence.py
pyrovelocity/metrics/trajectory.py
pyrovelocity/models/__init__.py
pyrovelocity/models/_deterministic_inference.py
pyrovelocity/models/_deterministic_simulation.py
pyrovelocity/models/_hyperparameter_calibration.py
pyrovelocity/models/_trainer.py
pyrovelocity/models/_transcription_dynamics.py
pyrovelocity/models/_velocity.py
pyrovelocity/models/_velocity_model.py
pyrovelocity/models/_velocity_module.py
pyrovelocity/plots/__init__.py
pyrovelocity/plots/_common.py
pyrovelocity/plots/_count_histograms.py
pyrovelocity/plots/_dynamics.py
pyrovelocity/plots/_experimental.py
pyrovelocity/plots/_genes.py
pyrovelocity/plots/_lineage_fate_correlation.py
pyrovelocity/plots/_parameters.py
pyrovelocity/plots/_predictive.py
pyrovelocity/plots/_rainbow.py
pyrovelocity/plots/_report.py
pyrovelocity/plots/_summary.py
pyrovelocity/plots/_time.py
pyrovelocity/plots/_uncertainty.py
pyrovelocity/plots/_vector_fields.py
pyrovelocity/plots/layout.py
pyrovelocity/plots/models.py
pyrovelocity/random_state.py
pyrovelocity/styles/__init__.py
pyrovelocity/styles/colors.py
pyrovelocity-0.4.5.dist-info/LICENSE
pyrovelocity-0.4.5.dist-info/METADATA
pyrovelocity-0.4.5.dist-info/WHEEL
pyrovelocity-0.4.5.dist-info/entry_points.txt
pyrovelocity-0.4.5.dist-info/RECORD
