Metadata-Version: 2.1
Name: pyrovelocity
Version: 0.4.5
Summary: A multivariate RNA Velocity model to estimate future cell states with uncertainty using probabilistic modeling with pyro.
Home-page: https://docs.pyrovelocity.net
License: AGPL-3.0-only
Author: pyrovelocity team
Requires-Python: >=3.11,<3.13
Classifier: Development Status :: 3 - Alpha
Classifier: Intended Audience :: Developers
Classifier: License :: OSI Approved :: GNU Affero General Public License v3
Classifier: Natural Language :: English
Classifier: Programming Language :: Python :: 3
Classifier: Programming Language :: Python :: 3.11
Classifier: Programming Language :: Python :: 3.12
Provides-Extra: bioinformatics
Provides-Extra: docs
Provides-Extra: lint
Provides-Extra: plotting
Provides-Extra: test
Provides-Extra: workflows
Requires-Dist: adjusttext (>=1.1.1)
Requires-Dist: altair (>=5.3.0)
Requires-Dist: anndata (>=0.10.5)
Requires-Dist: anyio (>=4.3.0)
Requires-Dist: appdirs (>=1.4.4)
Requires-Dist: arviz (>=0.17.1)
Requires-Dist: astropy (>=6.1.2)
Requires-Dist: beartype (>=0.18.5)
Requires-Dist: black (>=23.3.0) ; extra == "lint"
Requires-Dist: chex (>=0.1.7)
Requires-Dist: click (>=8.1.7)
Requires-Dist: colorlog (>=6.7.0)
Requires-Dist: coverage[toml] (>=6.2) ; extra == "test"
Requires-Dist: daft (>=0.1.2)
Requires-Dist: dataclasses-json (>=0.5.7) ; extra == "workflows"
Requires-Dist: diffrax (>=0.5.0)
Requires-Dist: dill (>=0.3.8)
Requires-Dist: diskcache (>=5.6.1)
Requires-Dist: duckdb (>=1.0.0)
Requires-Dist: dulwich (>=0.21.7) ; extra == "workflows"
Requires-Dist: einops (>=0.7.0)
Requires-Dist: expression (>=5.0.2)
Requires-Dist: flax (>=0.8.1)
Requires-Dist: flytekit (>=1.13.3) ; extra == "workflows"
Requires-Dist: frozenlist (>=1.1.1) ; python_version < "3.12"
Requires-Dist: fsspec (>=2024.3.0)
Requires-Dist: furo (>=2023.5.20) ; extra == "docs"
Requires-Dist: google-api-python-client (>=2.79.0) ; extra == "workflows"
Requires-Dist: greenlet (>=3.0.3)
Requires-Dist: h5py (>=3.9.0)
Requires-Dist: httpx (>=0.27.0)
Requires-Dist: hydra-core (>=1.3.2) ; extra == "workflows"
Requires-Dist: hydra-zen (>=0.12.1) ; extra == "workflows"
Requires-Dist: hypothesis (>=6.71.0) ; extra == "test"
Requires-Dist: ibis-framework[duckdb] (>=9.2.0)
Requires-Dist: ipdb (>=0.13.13) ; extra == "test"
Requires-Dist: ipython (>=8.11.0) ; extra == "test"
Requires-Dist: ipywidgets (>=8.0.0) ; extra == "workflows"
Requires-Dist: jax (>=0.4.23)
Requires-Dist: jaxlib (>=0.4.23)
Requires-Dist: jaxtyping (>=0.2.25)
Requires-Dist: jupyter-cache (>=0.6.1) ; extra == "docs"
Requires-Dist: jupyterlab (>=4.0.9) ; extra == "docs"
Requires-Dist: jupytext (>=1.16.0) ; extra == "docs" or extra == "workflows"
Requires-Dist: leidenalg (>=0.9.1)
Requires-Dist: lightning (>=2.0.0)
Requires-Dist: llvmlite (>=0.41.1) ; python_version < "3.12"
Requires-Dist: mashumaro (>=3.10) ; extra == "workflows"
Requires-Dist: matplotlib (>=3.9.1)
Requires-Dist: matplotlib-venn (>=0.11.9) ; extra == "plotting"
Requires-Dist: mlflow (>=2.13.0)
Requires-Dist: mypy (>=0.930) ; extra == "lint"
Requires-Dist: myst-parser (>=2.0.0) ; extra == "docs"
Requires-Dist: nbconvert (>=7.14.0) ; extra == "workflows"
Requires-Dist: nbformat (>=5.9.2) ; extra == "workflows"
Requires-Dist: nbsphinx (>=0.9.3) ; extra == "docs"
Requires-Dist: numpyro (>=0.15.0)
Requires-Dist: omegaconf (>=2.3.0) ; extra == "workflows"
Requires-Dist: pandas (>=2.0.0)
Requires-Dist: papermill (>=2.4.0) ; extra == "workflows"
Requires-Dist: pillow (>=10.1.0)
Requires-Dist: plumbum (>=1.8.2)
Requires-Dist: polars (>=0.20.17)
Requires-Dist: pre-commit (>=2.16.0) ; extra == "lint"
Requires-Dist: pre-commit-hooks (>=4.1.0) ; extra == "lint"
Requires-Dist: pyarrow (>=14.0.2)
Requires-Dist: pydantic (>=2.8.0)
Requires-Dist: pyensembl (>=2.3.12) ; extra == "bioinformatics"
Requires-Dist: pyfaidx (>=0.8.1.1) ; extra == "bioinformatics"
Requires-Dist: pygments (>=2.15.0) ; extra == "lint" or extra == "test"
Requires-Dist: pyro-ppl (>=1.9.1)
Requires-Dist: pytest (>=6.2.5) ; extra == "test"
Requires-Dist: pytest-asyncio (>=0.21.1) ; extra == "test"
Requires-Dist: pytest-cov (>=4.0.0) ; extra == "test"
Requires-Dist: pytest-mock (>=3.10.0) ; extra == "test"
Requires-Dist: pytest-xdist (>=3.1.0) ; extra == "test"
Requires-Dist: python-dotenv (>=1.0.0) ; extra == "workflows"
Requires-Dist: pytorch-lightning (>=2.0.0)
Requires-Dist: pyyaml (>=6.0.1)
Requires-Dist: quartodoc (>=0.7.2) ; extra == "docs"
Requires-Dist: returns (>=0.23.0)
Requires-Dist: rich (>=13.7.1)
Requires-Dist: rich-click (>=1.7.3) ; extra == "workflows"
Requires-Dist: ruff (>=0.1.5) ; extra == "lint"
Requires-Dist: scanpy (>=1.10.1)
Requires-Dist: scikit-learn (>=1.3.1)
Requires-Dist: scipy (>=1.10.1,<1.14.0)
Requires-Dist: scvelo (>=0.3.2)
Requires-Dist: scvi-tools (>=1.1.1)
Requires-Dist: seaborn (>=0.13.2)
Requires-Dist: sparse (>=0.15.4)
Requires-Dist: sphinx (>=7.0.1) ; extra == "docs"
Requires-Dist: sphinx-autobuild (>=2021.3.14) ; extra == "docs"
Requires-Dist: sphinx-autodoc-typehints (>=1.23.3) ; extra == "docs"
Requires-Dist: sphinx-click (>=4.4.0) ; extra == "docs"
Requires-Dist: sphinx-copybutton (>=0.5.2) ; extra == "docs"
Requires-Dist: sphinx-markdown-builder (>=0.6.6) ; extra == "docs"
Requires-Dist: statsmodels (>=0.14.2)
Requires-Dist: sympy (>=1.12)
Requires-Dist: termcolor (>=2.2.0)
Requires-Dist: tiledb (>=0.31.1)
Requires-Dist: torch (>=2.1.2) ; python_version < "3.12"
Requires-Dist: torchmetrics (>=1.2.1)
Requires-Dist: trio (>=0.26.0)
Requires-Dist: validators (>=0.33.0)
Requires-Dist: vegafusion (>=1.6.9)
Requires-Dist: vegafusion-python-embed (>=1.6.9)
Requires-Dist: vl-convert-python (>=1.6.0)
Requires-Dist: xdoctest[colors] (>=0.15.10) ; extra == "test"
Requires-Dist: zstandard (>=0.23.0)
Project-URL: Changelog, https://github.com/pinellolab/pyrovelocity/releases
Project-URL: Documentation, https://docs.pyrovelocity.net
Project-URL: Repository, https://github.com/pinellolab/pyrovelocity
